15            0 LOAD_FAST                0 (flag)
              2 LOAD_CONST               0 (None)
              4 LOAD_CONST               1 (6)
              6 BUILD_SLICE              2
              8 BINARY_SUBSCR
             10 LOAD_CONST               2 ('TCP1P{')
             12 COMPARE_OP               3 (!=)
             14 POP_JUMP_IF_FALSE       38
             16 LOAD_FAST                0 (flag)
             18 LOAD_CONST               3 (-1)
             20 LOAD_CONST               0 (None)
             22 BUILD_SLICE              2
             24 BINARY_SUBSCR
             26 LOAD_CONST               4 ('}')
             28 COMPARE_OP               3 (!=)
             30 POP_JUMP_IF_FALSE       38

 16          32 LOAD_GLOBAL              0 (oops)
             34 CALL_FUNCTION            0
             36 POP_TOP

 18     >>   38 LOAD_FAST                0 (flag)
             40 LOAD_CONST               1 (6)
             42 LOAD_CONST               5 (10)
             44 BUILD_SLICE              2
             46 BINARY_SUBSCR
             48 LOAD_CONST               6 ('byte')
             50 COMPARE_OP               2 (==)
             52 POP_JUMP_IF_FALSE       60

 19          54 LOAD_GLOBAL              1 (yeayy)
             56 CALL_FUNCTION            0
             58 POP_TOP

 21     >>   60 LOAD_FAST                0 (flag)
             62 LOAD_CONST               5 (10)
             64 BINARY_SUBSCR
             66 POP_JUMP_IF_FALSE       98
             68 LOAD_FAST                0 (flag)
             70 LOAD_CONST               7 (15)
             72 BINARY_SUBSCR
             74 POP_JUMP_IF_FALSE       98
             76 LOAD_FAST                0 (flag)
             78 LOAD_CONST               8 (18)
             80 BINARY_SUBSCR
             82 LOAD_GLOBAL              2 (chr)
             84 LOAD_CONST               9 (95)
             86 CALL_FUNCTION            1
             88 COMPARE_OP               3 (!=)
             90 POP_JUMP_IF_FALSE       98

 22          92 LOAD_GLOBAL              0 (oops)
             94 CALL_FUNCTION            0
             96 POP_TOP

 24     >>   98 LOAD_FAST                0 (flag)
            100 LOAD_CONST              10 (11)
            102 LOAD_CONST               7 (15)
            104 BUILD_SLICE              2
            106 BINARY_SUBSCR
            108 LOAD_CONST              11 ('code')
            110 COMPARE_OP               3 (!=)
            112 POP_JUMP_IF_FALSE      120

 25         114 LOAD_GLOBAL              0 (oops)
            116 CALL_FUNCTION            0
            118 POP_TOP

 27     >>  120 LOAD_FAST                0 (flag)
            122 LOAD_CONST              10 (11)
            124 BINARY_SUBSCR
            126 LOAD_FAST                0 (flag)
            128 LOAD_CONST              12 (1)
            130 BINARY_SUBSCR
            132 LOAD_METHOD              3 (lower)
            134 CALL_METHOD              0
            136 COMPARE_OP               2 (==)
            138 POP_JUMP_IF_FALSE      146

 28         140 LOAD_GLOBAL              1 (yeayy)
            142 CALL_FUNCTION            0
            144 POP_TOP

 30     >>  146 LOAD_FAST                0 (flag)
            148 LOAD_CONST              13 (12)
            150 BINARY_SUBSCR
            152 LOAD_GLOBAL              4 (ord)
            154 LOAD_FAST                0 (flag)
            156 LOAD_CONST              14 (20)
            158 BINARY_SUBSCR
            160 CALL_FUNCTION            1
            162 LOAD_CONST               1 (6)
            164 BINARY_SUBTRACT
            166 COMPARE_OP               2 (==)
            168 POP_JUMP_IF_FALSE      176

 31         170 LOAD_GLOBAL              1 (yeayy)
            172 CALL_FUNCTION            0
            174 POP_TOP

 33     >>  176 LOAD_GLOBAL              4 (ord)
            178 LOAD_FAST                0 (flag)
            180 LOAD_CONST              15 (16)
            182 BINARY_SUBSCR
            184 CALL_FUNCTION            1
            186 LOAD_CONST              16 (105)
            188 COMPARE_OP               3 (!=)
            190 POP_JUMP_IF_FALSE      214
            192 LOAD_GLOBAL              4 (ord)
            194 LOAD_FAST                0 (flag)
            196 LOAD_CONST              17 (17)
            198 BINARY_SUBSCR
            200 CALL_FUNCTION            1
            202 LOAD_CONST              18 (115)
            204 COMPARE_OP               3 (!=)
            206 POP_JUMP_IF_FALSE      214

 34         208 LOAD_GLOBAL              0 (oops)
            210 CALL_FUNCTION            0
            212 POP_TOP

 36     >>  214 LOAD_FAST                0 (flag)
            216 LOAD_CONST              19 (19)
            218 BINARY_SUBSCR
            220 LOAD_CONST              20 ('H')
            222 COMPARE_OP               3 (!=)
            224 POP_JUMP_IF_FALSE      232

 37         226 LOAD_GLOBAL              0 (oops)
            228 CALL_FUNCTION            0
            230 POP_TOP

 39     >>  232 LOAD_GLOBAL              4 (ord)
            234 LOAD_FAST                0 (flag)
            236 LOAD_CONST              14 (20)
            238 BINARY_SUBSCR
            240 CALL_FUNCTION            1
            242 LOAD_CONST              21 (117)
            244 COMPARE_OP               2 (==)
            246 POP_JUMP_IF_FALSE      254

 40         248 LOAD_GLOBAL              1 (yeayy)
            250 CALL_FUNCTION            0
            252 POP_TOP

 42     >>  254 LOAD_GLOBAL              4 (ord)
            256 LOAD_FAST                0 (flag)
            258 LOAD_CONST              22 (21)
            260 BINARY_SUBSCR
            262 CALL_FUNCTION            1
            264 LOAD_GLOBAL              4 (ord)
            266 LOAD_FAST                0 (flag)
            268 LOAD_CONST              23 (2)
            270 BINARY_SUBSCR
            272 CALL_FUNCTION            1
            274 LOAD_CONST               5 (10)
            276 BINARY_SUBTRACT
            278 COMPARE_OP               3 (!=)
            280 EXTENDED_ARG             1
            282 POP_JUMP_IF_FALSE      290

 43         284 LOAD_GLOBAL              0 (oops)
            286 CALL_FUNCTION            0
            288 POP_TOP

 45     >>  290 LOAD_FAST                0 (flag)
            292 LOAD_CONST              24 (22)
            294 BINARY_SUBSCR
            296 LOAD_FAST                0 (flag)
            298 LOAD_CONST              25 (0)
            300 BINARY_SUBSCR
            302 LOAD_METHOD              3 (lower)
            304 CALL_METHOD              0
            306 COMPARE_OP               3 (!=)
            308 EXTENDED_ARG             1
            310 POP_JUMP_IF_FALSE      318

 46         312 LOAD_GLOBAL              0 (oops)
            314 CALL_FUNCTION            0
            316 POP_TOP

 48     >>  318 LOAD_FAST                0 (flag)
            320 LOAD_CONST              24 (22)
            322 BINARY_SUBSCR
            324 LOAD_FAST                0 (flag)
            326 LOAD_CONST              26 (23)
            328 BINARY_SUBSCR
            330 COMPARE_OP               2 (==)
            332 EXTENDED_ARG             1
            334 POP_JUMP_IF_FALSE      342

 49         336 LOAD_GLOBAL              1 (yeayy)
            338 CALL_FUNCTION            0
            340 POP_TOP
        >>  342 LOAD_CONST               0 (None)
            344 RETURN_VALUE
